setup.py
agssearch/__init__.py
agssearch/agssearch.py
agssearch.egg-info/PKG-INFO
agssearch.egg-info/SOURCES.txt
agssearch.egg-info/dependency_links.txt
agssearch.egg-info/entry_points.txt
agssearch.egg-info/requires.txt
agssearch.egg-info/top_level.txt