Metadata-Version: 1.0
Name: agssearch
Version: 0.4
Summary: Python client for the German Destatis Gemeindeverzeichnis
Home-page: https://github.com/marians/agssearch
Author: Marian Steinbach
Author-email: marian@sendung.de
License: UNKNOWN
Platform: UNKNOWN
